{
  "version": "6702",
  "sections": [
    {
      "title": "World malaria report 2024",
      "description": "Overview of global malaria statistics.",
      "items": []
    },
    {
      "title":"WHO \nguidelines",
      "items": [
        { "subtitle": "Test. Treat. Track.", "description": "2023 update", "link": "https://who.int/report.pdf" }
      ]
    },
    {
      "title": "WHO malaria terminology",
      "items": [
        { "term": "Vector control", "definition": "Methods to kill mosquitoes." }
      ]
    }
  ]
}
